interpolator_for_wrfchem/__init__.py
interpolator_for_wrfchem/__main__.py
interpolator_for_wrfchem/global_models/__init__.py
interpolator_for_wrfchem/global_models/cams.py
interpolator_for_wrfchem/global_models/prototype.py
interpolator_for_wrfchem/interpolation.py
interpolator_for_wrfchem/res/__init__.py
interpolator_for_wrfchem/res/cams_l137.csv
interpolator_for_wrfchem/res/cams_l60.csv
interpolator_for_wrfchem/species_map.py
interpolator_for_wrfchem/utils.py
interpolator_for_wrfchem/wrf.py
interpolator_for_wrfchem-1.5.4.dist-info/METADATA
interpolator_for_wrfchem-1.5.4.dist-info/WHEEL
interpolator_for_wrfchem-1.5.4.dist-info/entry_points.txt
interpolator_for_wrfchem-1.5.4.dist-info/licenses/LICENSE
interpolator_for_wrfchem-1.5.4.dist-info/RECORD
