Metadata-Version: 2.4
Name: interpolator-for-wrfchem
Version: 1.5.4
Summary: Interpolates global chemistry fields for use with WRF-CHEM
License-File: LICENSE
Author: Thanasis Georgiou
Author-email: ageorgiou@noa.gr
Requires-Python: >=3.11,<4.0
Classifier: Programming Language :: Python :: 3
Classifier: Programming Language :: Python :: 3.11
Classifier: Programming Language :: Python :: 3.12
Classifier: Programming Language :: Python :: 3.13
Classifier: Programming Language :: Python :: 3.14
Requires-Dist: cftime (>=1.6.3,<2.0.0)
Requires-Dist: click (>=8.1.7,<9.0.0)
Requires-Dist: netcdf4 (>=1.7.2,<2.0.0)
Requires-Dist: numpy (>=2.2.5,<3.0.0)
Requires-Dist: pandas (>=2.2.3,<3.0.0)
Requires-Dist: scipy (>=1.15.3,<2.0.0)
Requires-Dist: tomli (>=2.0.1,<3.0.0)
Requires-Dist: xarray (>=2025.4.0,<2026.0.0)
